npy/__init__.py
npy/normalyze.py
npy-1.0.3.data/scripts/normalyze.py
npy-1.0.3.dist-info/METADATA
npy-1.0.3.dist-info/RECORD
npy-1.0.3.dist-info/WHEEL
npy-1.0.3.dist-info/top_level.txt
