Metadata-Version: 2.1
Name: npy
Version: 1.0.3
Summary: Normalize Python block and indentation technique.
Home-page: https://ZviWex.com
Author: ZviWex.
Author-email: zvikizviki@gmail.com
License: GNU
Platform: UNKNOWN
Classifier: Programming Language :: Python :: 2
Classifier: Operating System :: OS Independent
Requires-Python: ~=2.7
Requires-Dist: argparse
